{
  "title": {
    "indexPage": {
      "title": "Görev Tanımları",
      "subTitle": "Görev tanımlarınızı buradan yönetebilirsiniz"
    },
    "createPage": {
      "title": "Görev Tanımı Oluştur",
      "subTitle": "Çalışanlarınız için yeniş görev tanımı oluşturun"
    },
    "deletedPage": {
      "title": "Silinen Görev Tanımları",
      "subTitle": "Silinen görev tanımlarını kurtarabilir veya kalıcı olarak silebilirsiniz"
    }
  },
  "term": {
    "jobDescription": "Job Description | Job Descriptions",
    "code": "Kod",
    "name": "Görev Tanımı İsmi",
    "description": "Görev Tanımı Özeti",
    "staffType": "Kadro Tipi",
    "department": "Bağlı Olduğu Departman",
    "responsibilities": "Sorumlulukları",
    "powers": "Yetkileri",
    "requirements": "Gereklilikler",
    "skills": "Yetenekler",
    "workingConditions": "Çalışma Koşulları",
    "workingTools": "Çalışma Ekipmanları/Araçları",
    "workingHours": "Çalışma Saatleri",
    "overtimeStatus": "Fazla Mesai Durumu",
    "travelStatus": "Seyehat Durumu",
    "abroad": "Yurt dışı",
    "domestic": "Yurt içi",
    "whiteCollar": "Beyaz Yaka",
    "blueCollar": "Mavi Yaka"
  }
}